CHANGES.txt
COPYRIGHT.txt
LICENSE.txt
README.txt
ez_setup.py
setup.cfg
setup.py
repoze/__init__.py
repoze.whoplugins.zodb.egg-info/PKG-INFO
repoze.whoplugins.zodb.egg-info/SOURCES.txt
repoze.whoplugins.zodb.egg-info/dependency_links.txt
repoze.whoplugins.zodb.egg-info/namespace_packages.txt
repoze.whoplugins.zodb.egg-info/not-zip-safe
repoze.whoplugins.zodb.egg-info/requires.txt
repoze.whoplugins.zodb.egg-info/top_level.txt
repoze/who/__init__.py
repoze/who/plugins/__init__.py
repoze/who/plugins/zodb/__init__.py
repoze/who/plugins/zodb/impersonate.py
repoze/who/plugins/zodb/interfaces.py
repoze/who/plugins/zodb/tests.py
repoze/who/plugins/zodb/users.py